[
  
  {
  "id": "nirock-gurugram-01",
  "title": "Nirock Automotive Gurugram ITI Campus Placement 2026",
  "image": "campus photo/nirock.png",
  "company_name": "Nirock Automotive Private Limited",
  "location": "Gurugram, Haryana",
  "job_type": "Apprenticeship Trainee",
  "vacancy": "50",
  "note": "⚠️ आवश्यक सूचना: यह भर्ती पूरी तरह से निःशुल्क है। उम्मीदवारों को फॉर्मल कपड़े और जूते पहनकर आना अनिवार्य है। चप्पल, सैंडल या टी-शर्ट की अनुमति नहीं है।",
  "who_can_apply": [
    "Only Male Candidates",
    "Qualification: ITI Pass",
    "Age Limit: 18 to 28 Years",
    "Experience: Fresher"
  ],
  "responsibilities": [
    "Working as Assembly Operator",
    "Quality Engineering support",
    "Tool Room and Maintenance assistance",
    "Injection Moulding Machine Operation"
  ],
  "qualification": "ITI Passout",
  "salary": [
    "ITI Salary: ₹12,500 + ₹1,500 DBT (Total ₹14,000)",
    "Attendance Reward: ₹1,000/-",
    "Working Days: 6 Days a week",
    "Overtime: Single (As per company policy)",
    "Facilities: Canteen at ₹12/- per meal",
    "Uniform: Provided as per company policy",
    "Benefits: Medical Insurance Coverage of ₹2,00,000/-"
  ],
  "documents": [
    "Updated Resume",
    "Aadhar Card",
    "ITI Marksheet & Certificate",
    "Passport Size Photos"
  ],
  "date": "10.02.2026",
  "interview_time": "09:00 AM onwards",
  "interview_location": "Gurugram, Haryana (Job Fair / Rojgaar Sangam)",
  "contacts": [
    { "name": "HR Department", "phone": "232325546" }
  ],
  "map_link": ""
}
]